aramis_data_exporter-1.4.0.dist-info/licenses/LICENSE
aramis_exporter/__init__.py
aramis_exporter/client.py
aramis_exporter/constants.py
aramis_exporter/exporter.py
aramis_exporter/models.py
aramis_exporter/utils.py
aramis_exporter/test_data/aramis_projects/TestProject.aramis
aramis_exporter/test_data/aramis_projects/TestProjectPrepared.aramis
aramis_exporter/test_data/fem_results/0.00_0.00_150.00_nodemap.txt
aramis_exporter/test_data/fem_results/0.00_0.00_150.00_summary.json
aramis_exporter/test_data/fem_results/0.00_200.00_0.00_nodemap.txt
aramis_exporter/test_data/fem_results/0.00_200.00_0.00_summary.json
aramis_exporter/test_data/fem_results/0.00_200.00_150.00_nodemap.txt
aramis_exporter/test_data/fem_results/0.00_200.00_150.00_summary.json
aramis_exporter/test_data/fem_results/100.00_0.00_0.00_nodemap.txt
aramis_exporter/test_data/fem_results/100.00_0.00_0.00_summary.json
aramis_exporter/test_data/fem_results/100.00_0.00_150.00_nodemap.txt
aramis_exporter/test_data/fem_results/100.00_0.00_150.00_summary.json
aramis_exporter/test_data/fem_results/100.00_200.00_0.00_nodemap.txt
aramis_exporter/test_data/fem_results/100.00_200.00_0.00_summary.json
aramis_exporter/test_data/fem_results/100.00_200.00_150.00_nodemap.txt
aramis_exporter/test_data/fem_results/100.00_200.00_150.00_summary.json
aramis_exporter/test_data/images/0.00_0.00_150.00_nodemap_deformed_scipy_2.tiff
aramis_exporter/test_data/images/0.00_200.00_0.00_nodemap_deformed_scipy_1.tiff
aramis_exporter/test_data/images/0.00_200.00_150.00_nodemap_deformed_scipy_4.tiff
aramis_exporter/test_data/images/100.00_0.00_0.00_nodemap_deformed_scipy_3.tiff
aramis_exporter/test_data/images/100.00_0.00_150.00_nodemap_deformed_scipy_5.tiff
aramis_exporter/test_data/images/100.00_200.00_0.00_nodemap_deformed_scipy_6.tiff
aramis_exporter/test_data/images/100.00_200.00_150.00_nodemap_deformed_scipy_7.tiff
aramis_exporter/test_data/images/reference_0.tiff
aramis_exporter/test_data/nodemaps/TestProject_SP_SynLoads_dic_results_0_0.txt
aramis_data_exporter-1.4.0.dist-info/METADATA
aramis_data_exporter-1.4.0.dist-info/WHEEL
aramis_data_exporter-1.4.0.dist-info/top_level.txt
aramis_data_exporter-1.4.0.dist-info/RECORD
