Metadata-Version: 2.4
Name: aramis-data-exporter
Version: 1.4.0
Summary: Zeiss GOM Aramis Data Exporter
Author: Tobias Strohmann, Ferdinand Dömling, David Melching
Author-email: Eric Breitbarth <Eric.Breitbarth@dlr.de>
License-Expression: MIT
Project-URL: Repository, https://github.com/dlr-wf/aramis-data-exporter
Project-URL: Issues, https://github.com/dlr-wf/aramis-data-exporter/issues
Classifier: Programming Language :: Python :: 3
Requires-Python: >=3.8
License-File: LICENSE
Requires-Dist: numpy
Dynamic: license-file
